Workbook

Sheet Painel
A1: ="CALCULADORA DO PISO MÍNIMO DE FRETE "&Dados!D10&"" -> CALCULADORA DO PISO MÍNIMO DE FRETE TABELA A – CARGA LOTAÇÃO
E8: Piso Mínimo Frete de acordo com a RESOLUÇÃO Nº 6.076, DE 19 DE JANEIRO DE 2026.
E11: Carregado | F11: Retorno vazio | G11: Total Carregado + Vazio:
E12: =IF(ISERROR(Dados!D12),"Não existe dados",Dados!D12) -> 6795.48 | F12: =IF(ISERROR(Dados!D13),"Não existe dados",Dados!D13) -> 5667.568 | G12: =IF(ISERROR(Dados!$E$18),"",Dados!E$18) -> = R$ 12.463,05
B14: 1000 | E14: Valor por Ton: Carregado | F14: Valor por Ton: Vazio
E15: =IF(ISERROR(Dados!$C$18),"",Dados!C18) -> 339.774 | F15: =IF(ISERROR(Dados!$D$18),"",Dados!D18) -> 283.3784
B16: 20 | E16: =IF(ISERROR(Dados!$C$19),"",Dados!C19) -> Coeficiente de custo (CCD) = R$ 6,1604
E17: =IF(ISERROR(Dados!$C$20),"",Dados!C20) -> Carga e descarga (CC) = R$ 635,08
A19: COMO CALCULAR O PISO MÍNIMO
A21: Para calcular o valor mínimo do frete a ser realizado, sugere-se seguir o seguinte roteiro:
A22: 1. Defina primeiramente o tipo de carga a ser transportada, conforme opções apresentadas no Anexo II da Resolução ANTT nº 5.867/2020.
A24: 2. Na sequência, identifique a quantidade de eixos da composição veicular a ser utilizada no transporte;
A25: 3. Depois, identifique os coeficientes de custo de deslocamento (CCD) e de carga e descarga (CC) para a quantidade de eixos carregados da composição veicular que será usada:
A27: *Se o transportador for contratado para usar seu próprio veículo automotor e implemento rodoviário, usa-se a Tabela A do Anexo II da Resolução ANTT nº 5.867/2020; ou
A29: *Se o transportador for contratado para usar apenas o seu próprio veículo automotor, sendo o implemento rodoviário fornecido pelo contratante, usa-se a Tabela B do Anexo II da Resolução ANTT nº 5.867/2020.
A32: *Se o transportador for contratado para usar seu próprio veículo automotor e implemento rodoviário e for uma operação de transporte de alto desempenho, usa-se a Tabela C do Anexo II da Resolução ANTT nº 5.867/2020; ou
A35: Se o transportador for contratado para usar apenas o seu próprio veículo automotor e for uma operação de transporte de alto desempenho, sendo o implemento rodoviário fornecido pelo contratante, usa-se a Tabela D do Anexo II da Resolução ANTT nº 5.867/2020.
A38: Posteriormente, verifique a distância a ser percorrida na operação de transporte contratada; e
A39: Por fim, use os valores obtidos nos passos anteriores na seguinte expressão para o cálculo do Piso Mínimo de Frete em Reais por viagem (R$/viagem):
A41: PISO MINIMO DO FRETE (R$/viagem) = (DISTANCIA x CCD) + CC
A43: OBS.: Os valores, tais como tributos (IR, INSS, ICMS etc.), bem como o lucro e demais despesas deverão ser consideradas caso a caso, pois dependem do perfil de cada transportador ou da operação de transporte, podendo ser adicionadas ao valor do piso mínimo, a depender de negociação entre as partes. O valor do pedágio, quando houver, deverá ser obrigatoriamente acrescido aos pisos mínimos, devendo o pagamento ser realizado na forma da Lei nº 10.209, de 23 de março de 2001, e regulamentação vigente.

Sheet Dados
A1: Tipo de carga | B1: Números de Eixos
A2: Granel sólido | B2: 2 | C2: 1 | D2: TABELA A – CARGA LOTAÇÃO
A3: Granel líquido | B3: 3 | C3: 2 | D3: TABELA B – CARGA LOTAÇÃO, APENAS CONTRATAÇÃO DO VEÍCULO
A4: Frigorificada ou Aquecida | B4: 4 | C4: 3 | D4: TABELA C – CARRO DEDICADO
A5: Conteinerizada | B5: 5 | C5: 4 | D5: TABELA D – CARRO DEDICADO, APENAS CONTRATAÇÃO DO VEÍCULO
A6: Carga Geral | B6: 6
A7: Neogranel | B7: 7 | G7: =$B$11 -> 1
A8: Perigosa (granel sólido) | B8: 9 | C8: 1 | D8: CCD | E8: CC
A9: Perigosa (granel líquido) | C9: 5 | D9: =IF($C$8=1,VLOOKUP($C$9,'Tabela A'!$A$4:$I$15,Dados!$C$10+2),IF($C$8=2,VLOOKUP($C$9,'Tabela B'!A4:I15,Dados!$C$10+2),IF($C$8=3,VLOOKUP($C$9,'Tabela C'!$A$4:$I$15,Dados!$C$10+2),IF($C$8=4,VLOOKUP($C$9,'Tabela D'!$A$4:$I$15,Dados!$C$10+2))))) -> 6.1604 | E9: =IF($C$8=1,VLOOKUP($C$9,'Tabela A'!$J$4:$Q$15,Dados!$C$10+1),IF($C$8=2,VLOOKUP($C$9,'Tabela B'!$J$4:$Q$15,Dados!$C$10+1),IF($C$8=3,VLOOKUP($C$9,'Tabela C'!$J$4:$Q$15,Dados!$C$10+1),IF($C$8=4,VLOOKUP($C$9,'Tabela D'!$J$4:$Q$15,Dados!$C$10+1))))) -> 635.08
A10: Perigosa (frigorificada ou aquecida) | C10: 4 | D10: =VLOOKUP(Dados!$C$8,Dados!C2:D5,2) -> TABELA A – CARGA LOTAÇÃO
A11: Perigosa (conteinerizada) | B11: =C8 -> 1 | C11: 1
A12: Perigosa (carga geral) | B12: 1 | C12: NÃO | D12: =(Dados!$D$9*Painel!$B$14)+Dados!$E$9 -> 6795.48
A13: Carga Granel Pressurizada | B13: 2 | C13: SIM | D13: =((Painel!B14*Dados!D9)*92%) -> 5667.568
C15: =IF($B$11=1,VLOOKUP($G$7,$B$12:$D$13,3),IF($B$11=2,VLOOKUP($G$7,$B$12:$D$13,3))) -> 6795.48
C18: =(Painel!$E$12/Painel!$B$16) -> 339.774 | D18: =Painel!$F$12/Painel!$B$16 -> 283.3784 | E18: ="= "&DOLLAR(Painel!$E$12+Painel!$F$12)&"" -> = R$ 12.463,05
C19: ="Coeficiente de custo (CCD) = "&DOLLAR(Dados!$D$9,4&"") -> Coeficiente de custo (CCD) = R$ 6,1604
C20: ="Carga e descarga (CC) = "&DOLLAR(Dados!$E$9,2&"") -> Carga e descarga (CC) = R$ 635,08

Sheet Tabela A
B1: RESOLUÇÃO Nº 6.076, DE 19 DE JANEIRO DE 2026
C2: Coeficiente de custo (CCD) | K2: Carga e descarga (CC)
B3: Tipo de carga | C3: 2 | D3: 3 | E3: 4 | F3: 5 | G3: 6 | H3: 7 | I3: 9 | K3: 2 | L3: 3 | M3: 4 | N3: 5 | O3: 6 | P3: 7 | Q3: 9
A4: 1 | B4: Granel sólido | C4: 3.7123 | D4: 4.7427 | E4: 5.3672 | F4: 6.1859 | G4: 6.8058 | H4: 7.4505 | I4: 8.53 | J4: 1 | K4: 444.84 | L4: 533.36 | M4: 576.59 | N4: 642.1 | O4: 656.76 | P4: 792.3 | Q4: 877.83
A5: 2 | B5: Granel líquido | C5: 3.7837 | D5: 4.835 | E5: 5.5162 | F5: 6.348 | G5: 6.973 | H5: 7.5842 | I5: 8.6837 | J5: 2 | K5: 455.84 | L5: 550.1 | M5: 600.27 | N5: 669.38 | O5: 685.45 | P5: 811.76 | Q5: 902.8
A6: 3 | B6: Frigorificada ou Aquecida | C6: 4.3423 | D6: 5.5387 | E6: 6.3226 | F6: 7.2435 | G6: 7.9625 | H6: 8.8534 | I6: 10.0426 | J6: 3 | K6: 502.29 | L6: 601.96 | M6: 663.16 | N6: 732.07 | O6: 745.94 | P6: 949.16 | Q6: 1030.58
A7: 4 | B7: Conteinerizada | C7: - | D7: 4.7164 | E7: 5.2975 | F7: 6.1243 | G7: 6.7426 | H7: 7.4482 | I7: 8.4497 | J7: 4 | K7: - | L7: 526.13 | M7: 557.42 | N7: 625.16 | O7: 639.38 | P7: 791.67 | Q7: 855.76
A8: 5 | B8: Carga Geral | C8: 3.6815 | D8: 4.7062 | E8: 5.3386 | F8: 6.1604 | G8: 6.7774 | H8: 7.4902 | I8: 8.5104 | J8: 5 | K8: 436.39 | L8: 523.33 | M8: 568.72 | N8: 635.08 | O8: 648.95 | P8: 803.22 | Q8: 872.44
A9: 6 | B9: Neogranel | C9: 3.3488 | D9: 4.7048 | E9: 5.3649 | F9: 6.1604 | G9: 6.7774 | H9: 7.4902 | I9: 8.5104 | J9: 6 | K9: 436.39 | L9: 522.93 | M9: 575.96 | N9: 635.08 | O9: 648.95 | P9: 803.22 | Q9: 872.44
A10: 7 | B10: Perigosa (granel sólido) | C10: 4.456 | D10: 5.496 | E10: 6.156 | F10: 6.9747 | G10: 7.5946 | H10: 8.2569 | I10: 9.3441 | J10: 7 | K10: 587.98 | L10: 679.12 | M10: 727.28 | N10: 792.8 | O10: 807.45 | P10: 947.84 | Q10: 1035.49
A11: 8 | B11: Perigosa (granel líquido) | C11: 4.5395 | D11: 5.6004 | E11: 6.2857 | F11: 7.1175 | G11: 7.7425 | H11: 8.3713 | I11: 9.4785 | J11: 8 | K11: 610.96 | L11: 707.85 | M11: 762.95 | N11: 832.06 | O11: 848.13 | P11: 979.29 | Q11: 1072.44
A12: 9 | B12: Perigosa (frigorificada ou aquecida) | C12: 4.9296 | D12: 6.1385 | E12: 6.9381 | F12: 7.859 | G12: 8.578 | H12: 9.4918 | I12: 10.691 | J12: 9 | K12: 609.31 | L12: 712.41 | M12: 780.02 | N12: 848.93 | O12: 862.8 | P12: 1072.32 | Q12: 1156.49
A13: 10 | B13: Perigosa (conteinerizada) | C13: - | D13: 5.0876 | E13: 5.7042 | F13: 6.5311 | G13: 7.1493 | H13: 7.8726 | I13: 8.8818 | J13: 10 | K13: - | L13: 623.38 | M13: 659.6 | N13: 727.35 | O13: 741.56 | P13: 898.7 | Q13: 964.9
A14: 11 | B14: Perigosa (carga geral) | C14: 4.0432 | D14: 5.0774 | E14: 5.7453 | F14: 6.5671 | G14: 7.1841 | H14: 7.9146 | I14: 8.9424 | J14: 11 | K14: 531.01 | L14: 620.58 | M14: 670.91 | N14: 737.27 | O14: 751.14 | P14: 910.26 | Q14: 981.58
A15: 12 | B15: Carga Granel Pressurizada | C15: - | D15: - | E15: - | F15: 6.5125 | G15: 7.1739 | H15: - | I15: 9.0335 | J15: 12 | K15: - | L15: - | M15: - | N15: 731.9 | O15: 757.99 | P15: - | Q15: 1016.29

Sheet Tabela B
B1: ='Tabela A'!B1 -> RESOLUÇÃO Nº 6.076, DE 19 DE JANEIRO DE 2026
B2: Tipo de carga | C2: Coeficiente de custo (CCD) | K2: Carga e descarga (CC)
C3: 2 | D3: 3 | E3: 4 | F3: 5 | G3: 6 | H3: 7 | I3: 9 | K3: 2 | L3: 3 | M3: 4 | N3: 5 | O3: 6 | P3: 7 | Q3: 9
A4: 1 | B4: Granel sólido | C4: - | D4: - | E4: 4.7937 | F4: 5.4473 | G4: 6.0546 | H4: 6.4716 | I4: 7.1838 | J4: 1 | K4: - | L4: - | M4: 515.17 | N4: 574.29 | O4: 588.17 | P4: 695.68 | Q4: 746.78
A5: 2 | B5: Granel líquido | C5: - | D5: - | E5: 4.8566 | F5: 5.5102 | G5: 6.1175 | H5: 6.5345 | I5: 7.2467 | J5: 2 | K5: - | L5: - | M5: 515.17 | N5: 574.29 | O5: 588.17 | P5: 695.68 | Q5: 746.78
A6: 3 | B6: Frigorificada ou Aquecida | C6: - | D6: - | E6: 5.6121 | F6: 6.3555 | G6: 7.0649 | H6: 7.4995 | I6: 8.3441 | J6: 3 | K6: - | L6: - | M6: 564.07 | N6: 623.2 | O6: 637.07 | P6: 749.43 | Q6: 802.65
A7: 4 | B7: Conteinerizada | C7: - | D7: - | E7: 4.7937 | F7: 5.4473 | G7: 6.0546 | H7: 6.4716 | I7: 7.1838 | J7: 4 | K7: - | L7: - | M7: 515.17 | N7: 574.29 | O7: 588.17 | P7: 695.68 | Q7: 746.78
A8: 5 | B8: Carga Geral | C8: - | D8: - | E8: 4.7937 | F8: 5.4473 | G8: 6.0546 | H8: 6.4716 | I8: 7.1838 | J8: 5 | K8: - | L8: - | M8: 515.17 | N8: 574.29 | O8: 588.17 | P8: 695.68 | Q8: 746.78
A9: 6 | B9: Neogranel | C9: - | D9: - | E9: 4.7937 | F9: 5.4473 | G9: 6.0546 | H9: 6.4716 | I9: 7.1838 | J9: 6 | K9: - | L9: - | M9: 515.17 | N9: 574.29 | O9: 588.17 | P9: 695.68 | Q9: 746.78
A10: 7 | B10: Perigosa (granel sólido) | C10: - | D10: - | E10: 5.5825 | F10: 6.236 | G10: 6.8434 | H10: 7.278 | I10: 7.9979 | J10: 7 | K10: - | L10: - | M10: 665.87 | N10: 724.99 | O10: 738.86 | P10: 851.22 | Q10: 904.44
A11: 8 | B11: Perigosa (granel líquido) | C11: - | D11: - | E11: 5.626 | F11: 6.2796 | G11: 6.887 | H11: 7.3216 | I11: 8.0415 | J11: 8 | K11: - | L11: - | M11: 677.85 | N11: 736.97 | O11: 750.84 | P11: 863.2 | Q11: 916.42
A12: 9 | B12: Perigosa (frigorificada ou aquecida) | C12: - | D12: - | E12: 6.2276 | F12: 6.971 | G12: 7.6804 | H12: 8.138 | I12: 8.9925 | J12: 9 | K12: - | L12: - | M12: 680.93 | N12: 740.05 | O12: 753.93 | P12: 872.59 | Q12: 928.56
A13: 10 | B13: Perigosa (conteinerizada) | C13: - | D13: - | E13: 5.2004 | F13: 5.854 | G13: 6.4613 | H13: 6.896 | I13: 7.6158 | J13: 10 | K13: - | L13: - | M13: 617.35 | N13: 676.48 | O13: 690.35 | P13: 802.71 | Q13: 855.93
A14: 11 | B14: Perigosa (carga geral) | C14: - | D14: - | E14: 5.2004 | F14: 5.854 | G14: 6.4613 | H14: 6.896 | I14: 7.6158 | J14: 11 | K14: - | L14: - | M14: 617.35 | N14: 676.48 | O14: 690.35 | P14: 802.71 | Q14: 855.93
A15: 12 | B15: Carga Granel Pressurizada | C15: - | D15: - | E15: - | F15: 5.4473 | G15: 6.0546 | H15: - | I15: 7.1838 | J15: 12 | K15: - | L15: - | M15: - | N15: 574.29 | O15: 588.17 | P15: - | Q15: 746.78

Sheet Tabela C
B1: ='Tabela B'!B1 -> RESOLUÇÃO Nº 6.076, DE 19 DE JANEIRO DE 2026
B2: Tipo de carga | C2: Coeficiente de custo (CCD) | K2: Carga e descarga (CC)
C3: 2 | D3: 3 | E3: 4 | F3: 5 | G3: 6 | H3: 7 | I3: 9 | K3: 2 | L3: 3 | M3: 4 | N3: 5 | O3: 6 | P3: 7 | Q3: 9
A4: 1 | B4: Granel sólido | C4: 3.1154 | D4: 3.9624 | E4: 4.5292 | F4: 5.1952 | G4: 5.7809 | H4: 6.152 | I4: 7.0505 | J4: 1 | K4: 168.42 | L4: 191.28 | M4: 207.68 | N4: 221.79 | O4: 224.95 | P4: 261.12 | Q4: 282.59
A5: 2 | B5: Granel líquido | C5: 3.1612 | D5: 4.0158 | E5: 4.623 | F5: 5.2937 | G5: 5.8813 | H5: 6.2403 | I5: 7.146 | J5: 2 | K5: 170.79 | L5: 194.88 | M5: 212.78 | N5: 227.67 | O5: 231.13 | P5: 265.31 | Q5: 287.97
A6: 3 | B6: Frigorificada ou Aquecida | C6: 3.7196 | D6: 4.7135 | E6: 5.4105 | F6: 6.1709 | G6: 6.8575 | H6: 7.3296 | I6: 8.3531 | J6: 3 | K6: 198.62 | L6: 225.01 | M6: 247.41 | N6: 262.25 | O6: 265.24 | P6: 318.08 | Q6: 339.58
A7: 4 | B7: Conteinerizada | C7: - | D7: 3.953 | E7: 4.5041 | F7: 5.1731 | G7: 5.7582 | H7: 6.1511 | I7: 7.0217 | J7: 4 | K7: - | L7: 189.72 | M7: 203.55 | N7: 218.14 | O7: 221.21 | P7: 260.98 | Q7: 277.83
A8: 5 | B8: Carga Geral | C8: 3.1044 | D8: 3.9493 | E8: 4.5189 | F8: 5.186 | G8: 5.7707 | H8: 6.1662 | I8: 7.0435 | J8: 5 | K8: 166.6 | L8: 189.11 | M8: 205.98 | N8: 220.28 | O8: 223.27 | P8: 263.47 | Q8: 281.43
A9: 6 | B9: Neogranel | C9: 2.7717 | D9: 3.9488 | E9: 4.5283 | F9: 5.186 | G9: 5.7707 | H9: 6.1662 | I9: 7.0435 | J9: 6 | K9: 166.6 | L9: 189.03 | M9: 207.54 | N9: 220.28 | O9: 223.27 | P9: 263.47 | Q9: 281.43
A10: 7 | B10: Perigosa (granel sólido) | C10: 3.6335 | D10: 4.4909 | E10: 5.0945 | F10: 5.7605 | G10: 6.3462 | H10: 6.7363 | I10: 7.6431 | J10: 7 | K10: 217.08 | L10: 241.63 | M10: 261.22 | N10: 275.34 | O10: 278.5 | P10: 317.8 | Q10: 340.64
A11: 8 | B11: Perigosa (granel líquido) | C11: 3.6635 | D11: 4.5284 | E11: 5.1411 | F11: 5.8118 | G11: 6.3993 | H11: 6.7773 | I11: 7.6914 | J11: 8 | K11: 222.03 | L11: 247.82 | M11: 268.91 | N11: 283.8 | O11: 287.26 | P11: 324.57 | Q11: 348.6
A12: 9 | B12: Perigosa (frigorificada ou aquecida) | C12: 4.1978 | D12: 5.2051 | E12: 5.9198 | F12: 6.6801 | G12: 7.3668 | H12: 7.8636 | I12: 8.8978 | J12: 9 | K12: 244.84 | L12: 273.44 | M12: 299.98 | N12: 314.83 | O12: 317.82 | P12: 374.73 | Q12: 398.01
A13: 10 | B13: Perigosa (conteinerizada) | C13: - | D13: 4.2124 | E13: 4.8005 | F13: 5.4694 | G13: 6.0545 | H13: 6.4664 | I13: 7.3453 | J13: 10 | K13: - | L13: 229.62 | M13: 246.64 | N13: 261.24 | O13: 264.3 | P13: 307.21 | Q13: 325.43
A14: 11 | B14: Perigosa (carga geral) | C14: 3.3535 | D14: 4.2088 | E14: 4.8152 | F14: 5.4824 | G14: 6.067 | H14: 6.4815 | I14: 7.3671 | J14: 11 | K14: 204.81 | L14: 229.02 | M14: 249.08 | N14: 263.37 | O14: 266.36 | P14: 309.7 | Q14: 329.02
A15: 12 | B15: Carga Granel Pressurizada | C15: - | D15: - | E15: - | F15: 5.3125 | G15: 5.9131 | H15: - | I15: 7.2313 | J15: 12 | K15: - | L15: - | M15: - | N15: 241.14 | O15: 246.76 | P15: - | Q15: 312.42

Sheet Tabela D
B1: ='Tabela C'!B1 -> RESOLUÇÃO Nº 6.076, DE 19 DE JANEIRO DE 2026
B2: Tipo de carga | C2: Coeficiente de custo (CCD) | K2: Carga e descarga (CC)
C3: 2 | D3: 3 | E3: 4 | F3: 5 | G3: 6 | H3: 7 | I3: 9 | K3: 2 | L3: 3 | M3: 4 | N3: 5 | O3: 6 | P3: 7 | Q3: 9
A4: 1 | B4: Granel sólido | C4: - | D4: - | E4: 4.0988 | F4: 4.6146 | G4: 5.1896 | H4: 5.3982 | I4: 6.0097 | J4: 1 | K4: - | L4: - | M4: 194.44 | N4: 207.18 | O4: 210.17 | P4: 240.3 | Q4: 254.35
A5: 2 | B5: Granel líquido | C5: - | D5: - | E5: 4.1617 | F5: 4.6775 | G5: 5.2525 | H5: 5.4611 | I5: 6.0726 | J5: 2 | K5: - | L5: - | M5: 194.44 | N5: 207.18 | O5: 210.17 | P5: 240.3 | Q5: 254.35
A6: 3 | B6: Frigorificada ou Aquecida | C6: - | D6: - | E6: 4.9309 | F6: 5.5366 | G6: 6.2136 | H6: 6.4413 | I6: 7.1858 | J6: 3 | K6: - | L6: - | M6: 226.06 | N6: 238.8 | O6: 241.78 | P6: 275.04 | Q6: 290.47
A7: 4 | B7: Conteinerizada | C7: - | D7: - | E7: 4.0988 | F7: 4.6146 | G7: 5.1896 | H7: 5.3982 | I7: 6.0097 | J7: 4 | K7: - | L7: - | M7: 194.44 | N7: 207.18 | O7: 210.17 | P7: 240.3 | Q7: 254.35
A8: 5 | B8: Carga Geral | C8: - | D8: - | E8: 4.0988 | F8: 4.6146 | G8: 5.1896 | H8: 5.3982 | I8: 6.0097 | J8: 5 | K8: - | L8: - | M8: 194.44 | N8: 207.18 | O8: 210.17 | P8: 240.3 | Q8: 254.35
A9: 6 | B9: Neogranel | C9: - | D9: - | E9: 4.0988 | F9: 4.6146 | G9: 5.1896 | H9: 5.3982 | I9: 6.0097 | J9: 6 | K9: - | L9: - | M9: 194.44 | N9: 207.18 | O9: 210.17 | P9: 240.3 | Q9: 254.35
A10: 7 | B10: Perigosa (granel sólido) | C10: - | D10: - | E10: 4.6641 | F10: 5.1799 | G10: 5.7549 | H10: 5.9826 | I10: 6.6023 | J10: 7 | K10: - | L10: - | M10: 247.99 | N10: 260.73 | O10: 263.72 | P10: 296.98 | Q10: 312.4
A11: 8 | B11: Perigosa (granel líquido) | C11: - | D11: - | E11: 4.6797 | F11: 5.1955 | G11: 5.7706 | H11: 5.9982 | I11: 6.618 | J11: 8 | K11: - | L11: - | M11: 250.57 | N11: 263.31 | O11: 266.3 | P11: 299.56 | Q11: 314.98
A12: 9 | B12: Perigosa (frigorificada ou aquecida) | C12: - | D12: - | E12: 5.4402 | F12: 6.0458 | G12: 6.7229 | H12: 6.9752 | I12: 7.7305 | J12: 9 | K12: - | L12: - | M12: 278.63 | N12: 291.37 | O12: 294.36 | P12: 331.7 | Q12: 348.9
A13: 10 | B13: Perigosa (conteinerizada) | C13: - | D13: - | E13: 4.3951 | F13: 4.9109 | G13: 5.4859 | H13: 5.7136 | I13: 6.3333 | J13: 10 | K13: - | L13: - | M13: 237.54 | N13: 250.28 | O13: 253.27 | P13: 286.53 | Q13: 301.95
A14: 11 | B14: Perigosa (carga geral) | C14: - | D14: - | E14: 4.3951 | F14: 4.9109 | G14: 5.4859 | H14: 5.7136 | I14: 6.3333 | J14: 11 | K14: - | L14: - | M14: 237.54 | N14: 250.28 | O14: 253.27 | P14: 286.53 | Q14: 301.95
A15: 12 | B15: Carga Granel Pressurizada | C15: - | D15: - | E15: - | F15: 4.6146 | G15: 5.1896 | H15: - | I15: 6.0097 | J15: 12 | K15: - | L15: - | N15: 207.18 | O15: 210.17 | Q15: 254.35
